pong/__init__.py
pong/pong.py
pong/version.py
JPong-1.0.7.dist-info/LICENSE
JPong-1.0.7.dist-info/METADATA
JPong-1.0.7.dist-info/WHEEL
JPong-1.0.7.dist-info/entry_points.txt
JPong-1.0.7.dist-info/top_level.txt
JPong-1.0.7.dist-info/RECORD
