Metadata-Version: 2.1
Name: JPong
Version: 1.0.7
Summary: A simple Pong game written with Pygame
Home-page: UNKNOWN
Author: Jeff Moorhead
Author-email: Jeff.Moorhead1@gmail.com
License: UNKNOWN
Platform: UNKNOWN
Requires-Dist: pygame
